{"cameraMode":{"drawMode":0,"name":"Shaded","section":"Shading Mode"},"sceneLighting":true,"audioPlay":false,"sceneViewState":{"showFog":true,"showMaterialUpdate":false,"showSkybox":true,"showFlares":true,"showImageEffects":true,"showParticleSystems":true,"showVisualEffectGraphs":true,"m_FxEnabled":true},"in2DMode":false,"pivot":{"x":3.77382230758667,"y":3.2646965980529787,"z":111.31443786621094},"rotation":{"x":0.0654258280992508,"y":-0.7913528084754944,"z":0.08604889363050461,"w":0.6017228960990906},"size":3.6183953285217287,"orthographic":false}